vibrio.libs/libgcc_s-a04fdf82.so.1
vibrio.libs/libstdc++-a9383cce.so.6.0.28
vibrio-0.3.0.dist-info/LICENSE
vibrio-0.3.0.dist-info/WHEEL
vibrio-0.3.0.dist-info/METADATA
vibrio-0.3.0.dist-info/top_level.txt
vibrio-0.3.0.dist-info/RECORD
vibrio/__init__.py
vibrio/lazer.py
vibrio/types.py
vibrio/lib/Vibrio
