Metadata-Version: 2.1
Name: vibrio
Version: 0.3.0
License: MIT License
Requires-Python: >=3.9
License-File: LICENSE
Requires-Dist: requests
Requires-Dist: typing-extensions
Requires-Dist: aiohttp
Requires-Dist: psutil
